hydra_framework/__init__.py
hydra_framework/example.py
hydra_framework/hydra_common.py
hydra_framework/hydra_core.py
hydra_framework/hydra_net.py
hydra_framework/hydra_rest.py
hydra_framework-0.2.2.dist-info/METADATA
hydra_framework-0.2.2.dist-info/RECORD
hydra_framework-0.2.2.dist-info/WHEEL
hydra_framework-0.2.2.dist-info/top_level.txt
