Metadata-Version: 2.1
Name: hydra-framework
Version: 0.2.2
Summary: Python framework that provides the basic building blocks to implement data processing graphs.
Home-page: https://github.com/cyberpython/hydra
Author: George Migdos
Author-email: cyberpython@gmail.com
License: UNKNOWN
Platform: UNKNOWN
Classifier: Programming Language :: Python :: 3
Classifier: License :: OSI Approved :: MIT License
Classifier: Operating System :: OS Independent
Requires-Dist: Flask
